Sprint1JinDuong/__init__.py
Sprint1JinDuong/calculator.py
Sprint1JinDuong/demo.py
Sprint1JinDuong/test.py
sprint1jinduong-0.1.dist-info/LICENSE
sprint1jinduong-0.1.dist-info/WHEEL
sprint1jinduong-0.1.dist-info/METADATA
sprint1jinduong-0.1.dist-info/RECORD
