Metadata-Version: 2.1
Name: Sprint1JinDuong
Version: 0.1
Summary: This is the assignement to make a Calculator class,
Author-email: Jin Duong <jin040789@gmail.com>
Classifier: License :: OSI Approved :: MIT License
Project-URL: Home, https://github.com/JinNghiaDuong/Sprint_1
